{
    "categories": [
        {
            "name": "Hårdvara",
            "items": [
                {
                    "name": "Router",
                    "displayURL": "example.com",
                    "URL": "https://example.com",
                    "icon": "router"
                },
                {
                    "name": "NAS",
                    "displayURL": "example.com",
                    "URL": "https://example.com",
                    "icon": "storage"
                }
            ]
        },
        {
            "name": "Appar",
            "items": [
                {
                    "name": "PiHole",
                    "displayURL": "example.com",
                    "URL": "https://example.com",
                    "icon": "bar_chart"
                },
                {
                    "name": "Plex",
                    "displayURL": "example.com",
                    "URL": "https://example.com",
                    "icon": "tv"
                },
1			    {
                    "name": "Portainer",
                    "displayURL": "example.com",
                    "URL": "https://example.com",
                    "icon": "dns"
                }
            ]
        }
    ],
    "apps": [
        {
            "name": "NextCloud",
            "displayURL": "example.com",
            "URL": "https://example.com",
            "icon": "filter_drama"
        },
        {
            "name": "Ghost",
            "displayURL": "example.com",
            "URL": "https://example.com",
            "icon": "rss_feed"
        },
        {
            "name": "Bitwarden",
            "displayURL": "example.com",
            "URL": "https://example.com",
            "icon": "lock"
        },		
        {
            "name": "Minecraft",
            "displayURL": "example.com",
            "URL": "https://example.com",
            "icon": "videogame_asset"
        },
        {
            "name": "ESXi",
            "displayURL": "example.com",
            "URL": "https://example.com",
            "icon": "dns"
        }
    ]
}